{"node_id": 8107, "instances": [{"measurement_id": 10708, "measurement_desc_id": 1, "measurement_desc": "RTT measurement", "network_id": 2, "mcc": "242", "mnc": "02", "iccid": "08947080020202872524", "container": "dreibh/udpping", "start_time": "2024-08-22 00:00:00", "stop_time": "None"}, {"measurement_id": 10709, "measurement_desc_id": 16, "measurement_desc": "Combined speedtest.net and web page load test", "network_id": 2, "mcc": "242", "mnc": "02", "iccid": "08947080020202872524", "container": "dreibh/speedtest", "start_time": "2024-08-22 00:00:00", "stop_time": "None"}, {"measurement_id": 10710, "measurement_desc_id": 1, "measurement_desc": "RTT measurement", "network_id": 18, "mcc": "242", "mnc": "14", "iccid": "89470715000048638543", "container": "dreibh/udpping", "start_time": "2024-08-22 00:00:00", "stop_time": "None"}, {"measurement_id": 10711, "measurement_desc_id": 16, "measurement_desc": "Combined speedtest.net and web page load test", "network_id": 18, "mcc": "242", "mnc": "14", "iccid": "89470715000048638543", "container": "dreibh/speedtest", "start_time": "2024-08-22 00:00:00", "stop_time": "None"}]}