{"instances": [{"measurement_id": 6132, "measurement_desc": "RTT measurement", "stop_time": "None", "measurement_desc_id": 1, "network_id": 2, "container": "dreibh/udpping", "start_time": "2015-01-13 17:34:34", "mnc": "02", "mcc": "242"}, {"measurement_id": 6133, "measurement_desc": "RTT measurement", "stop_time": "None", "measurement_desc_id": 1, "network_id": 3, "container": "dreibh/udpping", "start_time": "2015-01-13 17:34:53", "mnc": "07", "mcc": "240"}, {"measurement_id": 6134, "measurement_desc": "RTT measurement", "stop_time": "None", "measurement_desc_id": 1, "network_id": 5, "container": "dreibh/udpping", "start_time": "2015-01-13 17:35:14", "mnc": "06", "mcc": "242"}, {"measurement_id": 6135, "measurement_desc": "RTT measurement", "stop_time": "None", "measurement_desc_id": 1, "network_id": 6, "container": "dreibh/udpping", "start_time": "2015-01-13 17:35:26", "mnc": null, "mcc": null}, {"measurement_id": 6313, "measurement_desc": "Huawei E392 mode switcher", "stop_time": "2015-03-09 14:53:15", "measurement_desc_id": 9, "network_id": 3, "container": null, "start_time": "2015-01-31 17:11:55", "mnc": "07", "mcc": "240"}, {"measurement_id": 6351, "measurement_desc": "HTTP download using curl", "stop_time": "2016-01-18 14:32:02", "measurement_desc_id": 2, "network_id": 3, "container": null, "start_time": "2015-01-31 21:10:27", "mnc": "07", "mcc": "240"}, {"measurement_id": 6447, "measurement_desc": "HTTP download using curl", "stop_time": "2015-03-16 14:39:57", "measurement_desc_id": 2, "network_id": 2, "container": null, "start_time": "2015-02-02 00:20:29", "mnc": "02", "mcc": "242"}, {"measurement_id": 7419, "measurement_desc": "HTTP download using curl", "stop_time": "2016-01-18 14:32:02", "measurement_desc_id": 2, "network_id": 3, "container": null, "start_time": "2015-09-18 14:44:32", "mnc": "07", "mcc": "240"}, {"measurement_id": 7420, "measurement_desc": "HTTP download using curl", "stop_time": "2016-12-20 11:41:50", "measurement_desc_id": 2, "network_id": 2, "container": null, "start_time": "2015-09-18 14:44:32", "mnc": "02", "mcc": "242"}, {"measurement_id": 8103, "measurement_desc": "Voip test", "stop_time": "2016-01-18 11:44:23", "measurement_desc_id": 3, "network_id": 3, "container": null, "start_time": "2015-11-17 17:17:20", "mnc": "07", "mcc": "240"}, {"measurement_id": 8104, "measurement_desc": "Voip test", "stop_time": "2016-01-18 11:44:23", "measurement_desc_id": 3, "network_id": 2, "container": null, "start_time": "2015-11-17 17:17:20", "mnc": "02", "mcc": "242"}, {"measurement_id": 8886, "measurement_desc": "Huawei E392 mode switcher", "stop_time": "2016-01-01 06:00:00", "measurement_desc_id": 9, "network_id": 3, "container": null, "start_time": "2015-12-11 15:09:36", "mnc": "07", "mcc": "240"}, {"measurement_id": 8887, "measurement_desc": "Huawei E392 mode switcher", "stop_time": "2016-01-01 06:00:00", "measurement_desc_id": 9, "network_id": 2, "container": null, "start_time": "2015-12-11 15:09:36", "mnc": "02", "mcc": "242"}, {"measurement_id": 9246, "measurement_desc": "Combined speedtest.net and web page load test", "stop_time": "None", "measurement_desc_id": 16, "network_id": 2, "container": null, "start_time": "2016-11-10 14:26:43", "mnc": "02", "mcc": "242"}], "node_id": 724}